[
    {
        "geometry": {
            "coordinates": [
                [
                    [
                        2077.013696,
                        1550.058624
                    ],
                    [
                        2135.513664,
                        1644.558592
                    ],
                    [
                        2157.013696,
                        1660.058624
                    ],
                    [
                        2205.513664,
                        1649.058624
                    ],
                    [
                        2263.513664,
                        1653.058624
                    ],
                    [
                        2287.513664,
                        1619.558592
                    ],
                    [
                        2245.013696,
                        1560.058624
                    ],
                    [
                        2221.513664,
                        1551.058624
                    ],
                    [
                        2198.513664,
                        1553.058624
                    ],
                    [
                        2146.013696,
                        1520.058624
                    ],
                    [
                        2103.013696,
                        1529.058624
                    ],
                    [
                        2077.013696,
                        1550.058624
                    ]
                ]
            ]
        }
    },
    {
        "geometry": {
            "coordinates": [
                [
                    [
                        962.949248,
                        1412.669952
                    ],
                    [
                        1004.949248,
                        1438.16992
                    ],
                    [
                        1045.949248,
                        1508.16992
                    ],
                    [
                        1030.449216,
                        1577.669952
                    ],
                    [
                        977.449216,
                        1598.16992
                    ],
                    [
                        913.449216,
                        1604.669952
                    ],
                    [
                        834.449216,
                        1612.669952
                    ],
                    [
                        788.949248,
                        1583.16992
                    ],
                    [
                        740.949248,
                        1566.669952
                    ],
                    [
                        702.449216,
                        1565.16992
                    ],
                    [
                        713.949248,
                        1494.669952
                    ],
                    [
                        686.449216,
                        1482.669952
                    ],
                    [
                        660.949248,
                        1475.16992
                    ],
                    [
                        689.374976,
                        1456.248064
                    ],
                    [
                        709.374976,
                        1475.748032
                    ],
                    [
                        730.374976,
                        1469.248064
                    ],
                    [
                        723.374976,
                        1443.748032
                    ],
                    [
                        746.374976,
                        1438.248064
                    ],
                    [
                        763.875008,
                        1452.248064
                    ],
                    [
                        797.374976,
                        1431.248064
                    ],
                    [
                        788.875008,
                        1409.748032
                    ],
                    [
                        810.374976,
                        1379.748032
                    ],
                    [
                        839.875008,
                        1387.248064
                    ],
                    [
                        855.374976,
                        1407.248064
                    ],
                    [
                        910.630848,
                        1398.0176
                    ],
                    [
                        945.630848,
                        1403.0176
                    ],
                    [
                        962.949248,
                        1412.669952
                    ]
                ]
            ]
        }
    },
    {
        "geometry": {
            "coordinates": [
                [
                    [
                        676.976576,
                        1015.703104
                    ],
                    [
                        678.476544,
                        1069.203136
                    ],
                    [
                        715.976576,
                        1099.703104
                    ],
                    [
                        752.476544,
                        1114.703104
                    ],
                    [
                        767.976576,
                        1129.203136
                    ],
                    [
                        787.976576,
                        1122.703104
                    ],
                    [
                        812.976576,
                        1135.703104
                    ],
                    [
                        838.976576,
                        1123.703104
                    ],
                    [
                        865.976576,
                        1090.703104
                    ],
                    [
                        867.976576,
                        1069.703104
                    ],
                    [
                        865.976576,
                        1061.203136
                    ],
                    [
                        883.476544,
                        1042.703104
                    ],
                    [
                        855.976576,
                        1035.203136
                    ],
                    [
                        832.476544,
                        994.703104
                    ],
                    [
                        804.476544,
                        966.203136
                    ],
                    [
                        773.476544,
                        967.203136
                    ],
                    [
                        741.976576,
                        979.203136
                    ],
                    [
                        698.976576,
                        965.703104
                    ],
                    [
                        672.476544,
                        989.203136
                    ],
                    [
                        656.476544,
                        990.203136
                    ],
                    [
                        676.976576,
                        1015.703104
                    ]
                ]
            ]
        }
    },
    {
        "geometry": {
            "coordinates": [
                [
                    [
                        891.085952,
                        846.96288
                    ],
                    [
                        889.58592,
                        887.462912
                    ],
                    [
                        933.085952,
                        893.462912
                    ],
                    [
                        989.58592,
                        874.462912
                    ],
                    [
                        1048.085952,
                        824.462912
                    ],
                    [
                        1055.58592,
                        782.462912
                    ],
                    [
                        1021.58592,
                        760.462912
                    ],
                    [
                        984.085952,
                        746.462912
                    ],
                    [
                        964.085952,
                        781.462912
                    ],
                    [
                        891.085952,
                        846.96288
                    ]
                ]
            ]
        }
    },
    {
        "geometry": {
            "coordinates": [
                [
                    [
                        1406.0,
                        1945.499968
                    ],
                    [
                        1415.500032,
                        2031.0
                    ],
                    [
                        1371.0,
                        2043.0
                    ],
                    [
                        1360.0,
                        2077.499968
                    ],
                    [
                        1381.0,
                        2080.499968
                    ],
                    [
                        1414.0,
                        2054.499968
                    ],
                    [
                        1424.0,
                        2120.499968
                    ],
                    [
                        1466.500032,
                        2141.0
                    ],
                    [
                        1468.0,
                        2167.974592
                    ],
                    [
                        1533.500032,
                        2209.474624
                    ],
                    [
                        1542.0,
                        2176.974592
                    ],
                    [
                        1557.500032,
                        2172.974592
                    ],
                    [
                        1565.500032,
                        2180.474624
                    ],
                    [
                        1575.500032,
                        2196.974592
                    ],
                    [
                        1625.500032,
                        2218.474624
                    ],
                    [
                        1649.500032,
                        2198.974592
                    ],
                    [
                        1683.500032,
                        2183.474624
                    ],
                    [
                        1674.0,
                        2158.974592
                    ],
                    [
                        1662.0,
                        2169.974592
                    ],
                    [
                        1561.500032,
                        2152.974592
                    ],
                    [
                        1520.0,
                        2125.474624
                    ],
                    [
                        1504.500032,
                        2094.974592
                    ],
                    [
                        1512.0,
                        2069.974592
                    ],
                    [
                        1499.500032,
                        2057.474624
                    ],
                    [
                        1514.0,
                        2047.974592
                    ],
                    [
                        1537.0,
                        2051.974592
                    ],
                    [
                        1553.500032,
                        2042.474624
                    ],
                    [
                        1537.500032,
                        2030.974592
                    ],
                    [
                        1516.500032,
                        2033.974592
                    ],
                    [
                        1505.500032,
                        2020.974592
                    ],
                    [
                        1465.500032,
                        2035.974592
                    ],
                    [
                        1428.500032,
                        1992.474624
                    ],
                    [
                        1420.0,
                        1952.974592
                    ],
                    [
                        1406.0,
                        1945.499968
                    ]
                ]
            ]
        }
    }
]