[
    {
        "geometry": {
            "coordinates": [
                [
                    [
                        2206.894912,
                        767.874304
                    ],
                    [
                        2262.889536,
                        878.927936
                    ],
                    [
                        2303.885632,
                        942.958848
                    ],
                    [
                        2314.884608,
                        969.971904
                    ],
                    [
                        2281.887744,
                        968.971392
                    ],
                    [
                        2292.88672,
                        1026.999424
                    ],
                    [
                        2305.88544,
                        1083.026496
                    ],
                    [
                        2262.889536,
                        1089.029376
                    ],
                    [
                        2240.891648,
                        1069.019712
                    ],
                    [
                        2157.899584,
                        788.88448
                    ],
                    [
                        2130.902144,
                        760.870912
                    ],
                    [
                        2136.901568,
                        733.857856
                    ],
                    [
                        2162.899072,
                        745.86368
                    ],
                    [
                        2206.894912,
                        767.874304
                    ]
                ]
            ]
        }
    },
    {
        "geometry": {
            "coordinates": [
                [
                    [
                        2436.87296,
                        865.921664
                    ],
                    [
                        2467.870016,
                        898.9376
                    ],
                    [
                        2515.865408,
                        933.954496
                    ],
                    [
                        2552.861888,
                        961.968
                    ],
                    [
                        2577.85952,
                        1010.99168
                    ],
                    [
                        2563.860864,
                        1032.001856
                    ],
                    [
                        2505.866368,
                        1025.998912
                    ],
                    [
                        2469.869824,
                        986.980096
                    ],
                    [
                        2427.873856,
                        932.953984
                    ],
                    [
                        2419.87456,
                        905.940992
                    ],
                    [
                        2401.876288,
                        870.924096
                    ],
                    [
                        2436.87296,
                        865.921664
                    ]
                ]
            ]
        }
    },
    {
        "geometry": {
            "coordinates": [
                [
                    [
                        2331.883008,
                        995.984448
                    ],
                    [
                        2408.875648,
                        1057.013888
                    ],
                    [
                        2475.869248,
                        1101.0352
                    ],
                    [
                        2514.865536,
                        1139.053504
                    ],
                    [
                        2580.859264,
                        1154.0608
                    ],
                    [
                        2608.856576,
                        1183.074752
                    ],
                    [
                        2598.857536,
                        1218.091712
                    ],
                    [
                        2562.860928,
                        1218.091712
                    ],
                    [
                        2514.865536,
                        1216.090752
                    ],
                    [
                        2487.868096,
                        1210.087808
                    ],
                    [
                        2442.872384,
                        1160.06368
                    ],
                    [
                        2357.880512,
                        1127.047744
                    ],
                    [
                        2316.884416,
                        1109.03904
                    ],
                    [
                        2304.885568,
                        1098.033728
                    ],
                    [
                        2293.886592,
                        996.98496
                    ],
                    [
                        2331.883008,
                        995.984448
                    ]
                ]
            ]
        }
    },
    {
        "geometry": {
            "coordinates": [
                [
                    [
                        2380.880512,
                        1297.099392
                    ],
                    [
                        2501.868992,
                        1345.122624
                    ],
                    [
                        2559.863424,
                        1388.14336
                    ],
                    [
                        2578.861632,
                        1442.169472
                    ],
                    [
                        2547.864576,
                        1461.178624
                    ],
                    [
                        2427.876032,
                        1376.1376
                    ],
                    [
                        2382.88032,
                        1331.11584
                    ],
                    [
                        2344.883904,
                        1303.102336
                    ],
                    [
                        2380.880512,
                        1297.099392
                    ]
                ]
            ]
        }
    },
    {
        "geometry": {
            "coordinates": [
                [
                    [
                        2290.897984,
                        1408.1168
                    ],
                    [
                        2349.892352,
                        1444.134208
                    ],
                    [
                        2404.887104,
                        1470.146752
                    ],
                    [
                        2438.88384,
                        1499.160768
                    ],
                    [
                        2455.88224,
                        1538.179584
                    ],
                    [
                        2405.886976,
                        1539.180096
                    ],
                    [
                        2354.89184,
                        1536.178624
                    ],
                    [
                        2282.898688,
                        1543.182016
                    ],
                    [
                        2249.901888,
                        1520.170944
                    ],
                    [
                        2245.902272,
                        1484.153536
                    ],
                    [
                        2254.901376,
                        1430.127424
                    ],
                    [
                        2290.897984,
                        1408.1168
                    ]
                ]
            ]
        }
    },
    {
        "geometry": {
            "coordinates": [
                [
                    [
                        1353.960128,
                        1706.486848
                    ],
                    [
                        1294.96576,
                        1740.503296
                    ],
                    [
                        1260.969024,
                        1754.510016
                    ],
                    [
                        1227.97216,
                        1804.534208
                    ],
                    [
                        1239.971008,
                        1833.54816
                    ],
                    [
                        1279.967168,
                        1872.56704
                    ],
                    [
                        1301.96512,
                        1908.584448
                    ],
                    [
                        1316.963648,
                        1951.605184
                    ],
                    [
                        1375.958016,
                        1973.615808
                    ],
                    [
                        1432.952576,
                        1982.62016
                    ],
                    [
                        1460.949952,
                        1898.579584
                    ],
                    [
                        1469.949056,
                        1841.552064
                    ],
                    [
                        1461.949824,
                        1774.51968
                    ],
                    [
                        1420.953728,
                        1725.496
                    ],
                    [
                        1402.955456,
                        1710.488768
                    ],
                    [
                        1353.960128,
                        1706.486848
                    ]
                ]
            ]
        }
    },
    {
        "geometry": {
            "coordinates": [
                [
                    [
                        2086.952064,
                        1871.257216
                    ],
                    [
                        2099.950848,
                        1932.286656
                    ],
                    [
                        2123.448576,
                        1950.29536
                    ],
                    [
                        2131.947776,
                        1926.283776
                    ],
                    [
                        2144.446592,
                        1911.776768
                    ],
                    [
                        2157.94528,
                        1918.279872
                    ],
                    [
                        2167.444416,
                        1898.770496
                    ],
                    [
                        2182.942912,
                        1893.768064
                    ],
                    [
                        2175.943616,
                        1949.795136
                    ],
                    [
                        2189.942272,
                        2009.32384
                    ],
                    [
                        2193.941888,
                        2044.841024
                    ],
                    [
                        2138.447168,
                        2007.32288
                    ],
                    [
                        2086.952064,
                        2014.326272
                    ],
                    [
                        2063.454336,
                        2024.83136
                    ],
                    [
                        2036.456896,
                        2007.823104
                    ],
                    [
                        2054.455168,
                        1978.809088
                    ],
                    [
                        2046.955904,
                        1947.794112
                    ],
                    [
                        2027.957696,
                        1920.78112
                    ],
                    [
                        2034.957056,
                        1903.27264
                    ],
                    [
                        2067.95392,
                        1889.766144
                    ],
                    [
                        2086.952064,
                        1871.257216
                    ]
                ]
            ]
        }
    },
    {
        "geometry": {
            "coordinates": [
                [
                    [
                        1235.987648,
                        2394.878208
                    ],
                    [
                        1223.488832,
                        2416.888832
                    ],
                    [
                        1223.488832,
                        2444.402112
                    ],
                    [
                        1157.495168,
                        2503.93088
                    ],
                    [
                        1134.497344,
                        2519.93856
                    ],
                    [
                        1121.998528,
                        2545.45088
                    ],
                    [
                        1155.495296,
                        2562.95936
                    ],
                    [
                        1184.992512,
                        2565.960832
                    ],
                    [
                        1215.989568,
                        2529.4432
                    ],
                    [
                        1233.98784,
                        2503.93088
                    ],
                    [
                        1241.987072,
                        2473.416128
                    ],
                    [
                        1265.984768,
                        2450.404992
                    ],
                    [
                        1278.483584,
                        2449.904768
                    ],
                    [
                        1265.484864,
                        2437.39872
                    ],
                    [
                        1250.98624,
                        2420.890752
                    ],
                    [
                        1250.486272,
                        2400.881088
                    ],
                    [
                        1235.987648,
                        2394.878208
                    ]
                ]
            ]
        }
    },
    {
        "geometry": {
            "coordinates": [
                [
                    [
                        2407.414976,
                        1734.714688
                    ],
                    [
                        2440.41184,
                        1780.236672
                    ],
                    [
                        2450.41088,
                        1812.752384
                    ],
                    [
                        2507.905408,
                        1833.762496
                    ],
                    [
                        2521.404096,
                        1880.785216
                    ],
                    [
                        2581.898368,
                        1880.284992
                    ],
                    [
                        2619.89472,
                        1867.778944
                    ],
                    [
                        2619.394752,
                        1823.257408
                    ],
                    [
                        2588.897664,
                        1778.735936
                    ],
                    [
                        2565.399936,
                        1759.726784
                    ],
                    [
                        2494.406656,
                        1738.716608
                    ],
                    [
                        2437.912064,
                        1738.216384
                    ],
                    [
                        2407.414976,
                        1734.714688
                    ]
                ]
            ]
        }
    }
]