[
    {
        "geometry": {
            "coordinates": [
                [
                    [
                        8498.234304,
                        4732.835072
                    ],
                    [
                        8226.291392,
                        4814.801664
                    ],
                    [
                        8196.297728,
                        4994.728384
                    ],
                    [
                        8194.298112,
                        5170.65664
                    ],
                    [
                        8414.251968,
                        5330.591488
                    ],
                    [
                        8632.206208,
                        5392.566272
                    ],
                    [
                        8968.13568,
                        5428.551616
                    ],
                    [
                        9110.105856,
                        5360.579264
                    ],
                    [
                        9166.094144,
                        5168.657472
                    ],
                    [
                        9064.11552,
                        4976.73568
                    ],
                    [
                        8852.16,
                        4828.795968
                    ],
                    [
                        8642.204096,
                        4760.82368
                    ],
                    [
                        8498.234304,
                        4732.835072
                    ]
                ]
            ]
        }
    },
    {
        "geometry": {
            "coordinates": [
                [
                    [
                        6560.245632,
                        1122.800064
                    ],
                    [
                        7012.150784,
                        894.892928
                    ],
                    [
                        6890.176384,
                        491.057472
                    ],
                    [
                        6626.231808,
                        457.071296
                    ],
                    [
                        6408.277568,
                        515.04768
                    ],
                    [
                        6250.31072,
                        625.00288
                    ],
                    [
                        6200.321216,
                        746.953216
                    ],
                    [
                        6192.32288,
                        908.887232
                    ],
                    [
                        6272.306112,
                        1056.826944
                    ],
                    [
                        6284.303616,
                        1130.7968
                    ],
                    [
                        6450.830848,
                        1193.302656
                    ],
                    [
                        6560.245632,
                        1122.800064
                    ]
                ]
            ]
        }
    },
    {
        "geometry": {
            "coordinates": [
                [
                    [
                        7644.580224,
                        909.418304
                    ],
                    [
                        7454.620096,
                        1121.331968
                    ],
                    [
                        7402.63104,
                        1341.242368
                    ],
                    [
                        7494.611712,
                        1559.1536
                    ],
                    [
                        7816.544128,
                        1679.104704
                    ],
                    [
                        8016.502144,
                        1695.098176
                    ],
                    [
                        8194.464768,
                        1579.145408
                    ],
                    [
                        8264.450112,
                        1337.244032
                    ],
                    [
                        8172.469376,
                        1079.34912
                    ],
                    [
                        7972.51136,
                        859.43872
                    ],
                    [
                        7788.550016,
                        859.43872
                    ],
                    [
                        7622.584832,
                        907.419136
                    ],
                    [
                        7644.580224,
                        909.418304
                    ]
                ]
            ]
        }
    },
    {
        "geometry": {
            "coordinates": [
                [
                    [
                        9059.701184,
                        497.001216
                    ],
                    [
                        8987.716288,
                        748.89856
                    ],
                    [
                        9039.705408,
                        928.82528
                    ],
                    [
                        9239.663424,
                        1048.776384
                    ],
                    [
                        9243.662592,
                        1196.716096
                    ],
                    [
                        9131.68608,
                        1320.6656
                    ],
                    [
                        8979.718016,
                        1452.61184
                    ],
                    [
                        8799.755776,
                        1660.527104
                    ],
                    [
                        8699.776768,
                        1776.479872
                    ],
                    [
                        8587.800256,
                        1980.3968
                    ],
                    [
                        8539.810368,
                        2096.349504
                    ],
                    [
                        8575.802816,
                        2276.276224
                    ],
                    [
                        8659.785152,
                        2376.235456
                    ],
                    [
                        9027.707904,
                        2452.204544
                    ],
                    [
                        9451.618944,
                        2300.266432
                    ],
                    [
                        9575.592896,
                        2176.316928
                    ],
                    [
                        9683.57024,
                        1984.395136
                    ],
                    [
                        9855.534144,
                        1752.489664
                    ],
                    [
                        9955.513152,
                        1608.548288
                    ],
                    [
                        10059.491328,
                        1476.602048
                    ],
                    [
                        10187.464448,
                        1308.670464
                    ],
                    [
                        10259.449344,
                        1248.694912
                    ],
                    [
                        10411.417408,
                        1088.760128
                    ],
                    [
                        10419.415744,
                        936.822016
                    ],
                    [
                        10199.461952,
                        660.9344
                    ],
                    [
                        9931.518208,
                        568.971904
                    ],
                    [
                        9639.579456,
                        536.98496
                    ],
                    [
                        9407.62816,
                        465.014272
                    ],
                    [
                        9203.670976,
                        409.037056
                    ],
                    [
                        9059.701184,
                        497.001216
                    ]
                ]
            ]
        }
    },
    {
        "geometry": {
            "coordinates": [
                [
                    [
                        11335.223488,
                        1584.55808
                    ],
                    [
                        11443.200832,
                        1924.419584
                    ],
                    [
                        11639.15968,
                        2128.336512
                    ],
                    [
                        11940.345984,
                        2204.589056
                    ],
                    [
                        12160.29984,
                        2184.597184
                    ],
                    [
                        12264.277952,
                        2064.64608
                    ],
                    [
                        12268.27712,
                        1808.750336
                    ],
                    [
                        12036.325824,
                        1632.822016
                    ],
                    [
                        11664.408128,
                        1508.875776
                    ],
                    [
                        11452.452608,
                        1484.885568
                    ],
                    [
                        11380.467712,
                        1508.875776
                    ],
                    [
                        11335.223488,
                        1584.55808
                    ]
                ]
            ]
        }
    },
    {
        "geometry": {
            "coordinates": [
                [
                    [
                        11528.436672,
                        2248.574336
                    ],
                    [
                        11852.36864,
                        2476.481472
                    ],
                    [
                        12056.325824,
                        2484.478208
                    ],
                    [
                        12360.262016,
                        2504.47008
                    ],
                    [
                        12592.213312,
                        2464.4864
                    ],
                    [
                        12780.173888,
                        2560.447296
                    ],
                    [
                        12832.162944,
                        2728.37888
                    ],
                    [
                        12760.178048,
                        2928.297408
                    ],
                    [
                        12452.242688,
                        3040.251776
                    ],
                    [
                        11900.358592,
                        3004.266432
                    ],
                    [
                        11548.432448,
                        2768.36256
                    ],
                    [
                        11312.481984,
                        2644.413056
                    ],
                    [
                        11096.652416,
                        2544.678656
                    ],
                    [
                        11168.637312,
                        2316.77152
                    ],
                    [
                        11192.632256,
                        2244.800832
                    ],
                    [
                        11396.58944,
                        2216.812224
                    ],
                    [
                        11528.436672,
                        2248.574336
                    ]
                ]
            ]
        }
    },
    {
        "geometry": {
            "coordinates": [
                [
                    [
                        11776.509696,
                        1461.120128
                    ],
                    [
                        12076.44672,
                        1629.051712
                    ],
                    [
                        12368.385472,
                        1661.03872
                    ],
                    [
                        12520.353536,
                        1657.04032
                    ],
                    [
                        12624.331712,
                        1493.107136
                    ],
                    [
                        12600.336768,
                        1301.185344
                    ],
                    [
                        12484.361088,
                        1097.268416
                    ],
                    [
                        12352.3888,
                        993.310784
                    ],
                    [
                        12100.441664,
                        865.36288
                    ],
                    [
                        11848.494592,
                        865.36288
                    ],
                    [
                        11704.5248,
                        905.346624
                    ],
                    [
                        11588.549184,
                        1049.287936
                    ],
                    [
                        11576.55168,
                        1197.227712
                    ],
                    [
                        11620.542464,
                        1345.167424
                    ],
                    [
                        11668.532352,
                        1401.144576
                    ],
                    [
                        11776.509696,
                        1461.120128
                    ]
                ]
            ]
        }
    },
    {
        "geometry": {
            "coordinates": [
                [
                    [
                        12648.326656,
                        801.388992
                    ],
                    [
                        12804.293952,
                        1061.283072
                    ],
                    [
                        12960.261184,
                        1153.245632
                    ],
                    [
                        13200.210816,
                        1109.263552
                    ],
                    [
                        13452.157952,
                        1021.299392
                    ],
                    [
                        13568.133568,
                        881.356416
                    ],
                    [
                        13588.129408,
                        701.429696
                    ],
                    [
                        13608.125184,
                        553.489984
                    ],
                    [
                        13488.1504,
                        393.555136
                    ],
                    [
                        13268.196544,
                        321.584512
                    ],
                    [
                        12980.257024,
                        321.584512
                    ],
                    [
                        12772.300672,
                        349.573056
                    ],
                    [
                        12604.335936,
                        381.560064
                    ],
                    [
                        12528.351872,
                        577.480192
                    ],
                    [
                        12556.345984,
                        669.442752
                    ],
                    [
                        12648.326656,
                        801.388992
                    ]
                ]
            ]
        }
    },
    {
        "geometry": {
            "coordinates": [
                [
                    [
                        17827.239424,
                        2408.734016
                    ],
                    [
                        17415.325952,
                        2460.712832
                    ],
                    [
                        17275.355328,
                        2592.659072
                    ],
                    [
                        17071.398144,
                        2800.574336
                    ],
                    [
                        17019.409024,
                        2984.499392
                    ],
                    [
                        17155.38048,
                        3196.413056
                    ],
                    [
                        17215.367872,
                        3308.367424
                    ],
                    [
                        17287.352768,
                        3540.27296
                    ],
                    [
                        17291.351936,
                        3708.204544
                    ],
                    [
                        17399.32928,
                        3984.092096
                    ],
                    [
                        17503.307456,
                        4040.069312
                    ],
                    [
                        17839.236928,
                        4052.064384
                    ],
                    [
                        18071.188224,
                        3948.106752
                    ],
                    [
                        18323.13536,
                        3796.168704
                    ],
                    [
                        18471.104256,
                        3604.246912
                    ],
                    [
                        18543.089152,
                        3444.312064
                    ],
                    [
                        18691.058112,
                        3372.341376
                    ],
                    [
                        18819.031232,
                        3164.426112
                    ],
                    [
                        18855.02368,
                        2860.549952
                    ],
                    [
                        18887.01696,
                        2604.654208
                    ],
                    [
                        18875.019456,
                        2288.782912
                    ],
                    [
                        18675.06144,
                        2040.883904
                    ],
                    [
                        18375.124416,
                        1984.906752
                    ],
                    [
                        17991.205056,
                        2260.794304
                    ],
                    [
                        17919.47808,
                        2346.048256
                    ],
                    [
                        17827.239424,
                        2408.734016
                    ]
                ]
            ]
        }
    },
    {
        "geometry": {
            "coordinates": [
                [
                    [
                        15783.301568,
                        4056.37888
                    ],
                    [
                        15503.36032,
                        4296.281088
                    ],
                    [
                        15551.350272,
                        4644.139392
                    ],
                    [
                        15847.288128,
                        4796.07744
                    ],
                    [
                        16159.222656,
                        4812.070912
                    ],
                    [
                        16388.353536,
                        4612.978432
                    ],
                    [
                        16324.366976,
                        4309.102208
                    ],
                    [
                        16196.393856,
                        4117.180416
                    ],
                    [
                        15920.451776,
                        4065.2016
                    ],
                    [
                        15783.301568,
                        4056.37888
                    ]
                ]
            ]
        }
    },
    {
        "geometry": {
            "coordinates": [
                [
                    [
                        16824.262016,
                        4796.903488
                    ],
                    [
                        16636.301504,
                        5068.792704
                    ],
                    [
                        16696.288896,
                        5328.686784
                    ],
                    [
                        16780.271296,
                        5496.618368
                    ],
                    [
                        17060.21248,
                        5612.571136
                    ],
                    [
                        17356.1504,
                        5540.600448
                    ],
                    [
                        17440.132736,
                        5448.637888
                    ],
                    [
                        17460.128512,
                        5268.711232
                    ],
                    [
                        17484.12352,
                        5068.792704
                    ],
                    [
                        17320.157952,
                        4924.851328
                    ],
                    [
                        17024.220032,
                        4784.908352
                    ],
                    [
                        16824.262016,
                        4796.903488
                    ]
                ]
            ]
        }
    },
    {
        "geometry": {
            "coordinates": [
                [
                    [
                        13584.94208,
                        5436.642816
                    ],
                    [
                        13312.999168,
                        5572.587392
                    ],
                    [
                        13316.998336,
                        5904.45216
                    ],
                    [
                        13452.969792,
                        6076.382144
                    ],
                    [
                        13816.893376,
                        6076.382144
                    ],
                    [
                        14168.81952,
                        5836.479872
                    ],
                    [
                        14216.809408,
                        5676.545024
                    ],
                    [
                        14192.814464,
                        5548.597184
                    ],
                    [
                        14040.846336,
                        5460.633024
                    ],
                    [
                        13844.887488,
                        5376.6672
                    ],
                    [
                        13724.912704,
                        5380.6656
                    ],
                    [
                        13584.94208,
                        5436.642816
                    ]
                ]
            ]
        }
    },
    {
        "geometry": {
            "coordinates": [
                [
                    [
                        15672.503808,
                        5060.795968
                    ],
                    [
                        15468.546624,
                        5228.727488
                    ],
                    [
                        15356.570176,
                        5356.675392
                    ],
                    [
                        15368.567616,
                        5532.603712
                    ],
                    [
                        15520.535744,
                        5688.54016
                    ],
                    [
                        15812.474432,
                        5712.530368
                    ],
                    [
                        15972.440832,
                        5668.548288
                    ],
                    [
                        16112.411456,
                        5548.597184
                    ],
                    [
                        16172.398848,
                        5488.621632
                    ],
                    [
                        16196.393856,
                        5312.693312
                    ],
                    [
                        16148.403904,
                        5152.758464
                    ],
                    [
                        15944.44672,
                        5060.795968
                    ],
                    [
                        15768.483648,
                        5048.800832
                    ],
                    [
                        15672.503808,
                        5060.795968
                    ]
                ]
            ]
        }
    },
    {
        "geometry": {
            "coordinates": [
                [
                    [
                        14684.711168,
                        5364.672128
                    ],
                    [
                        14536.742272,
                        5516.610176
                    ],
                    [
                        14472.755712,
                        5576.585792
                    ],
                    [
                        14424.76576,
                        5736.520576
                    ],
                    [
                        14436.763264,
                        5884.460288
                    ],
                    [
                        14552.73888,
                        5960.429376
                    ],
                    [
                        14808.685184,
                        5984.419584
                    ],
                    [
                        15016.641536,
                        5984.419584
                    ],
                    [
                        15184.606272,
                        5868.466816
                    ],
                    [
                        15240.594496,
                        5760.510848
                    ],
                    [
                        15232.59616,
                        5524.606976
                    ],
                    [
                        15052.633984,
                        5428.64608
                    ],
                    [
                        14932.659136,
                        5352.676992
                    ],
                    [
                        14684.711168,
                        5364.672128
                    ]
                ]
            ]
        }
    },
    {
        "geometry": {
            "coordinates": [
                [
                    [
                        15104.62304,
                        6260.3072
                    ],
                    [
                        14716.704448,
                        6212.32672
                    ],
                    [
                        14564.736384,
                        6408.246912
                    ],
                    [
                        14536.742272,
                        6632.155648
                    ],
                    [
                        14640.720448,
                        6836.072576
                    ],
                    [
                        14828.68096,
                        7019.997632
                    ],
                    [
                        15004.644032,
                        7271.894976
                    ],
                    [
                        15068.630592,
                        7375.852608
                    ],
                    [
                        15360.56928,
                        7579.769536
                    ],
                    [
                        15588.521472,
                        7655.73856
                    ],
                    [
                        15848.46688,
                        7579.769536
                    ],
                    [
                        16060.4224,
                        7479.81024
                    ],
                    [
                        16156.40224,
                        7315.877056
                    ],
                    [
                        16284.37536,
                        7135.9504
                    ],
                    [
                        16248.382912,
                        6980.013888
                    ],
                    [
                        15952.445056,
                        6792.090496
                    ],
                    [
                        15704.497088,
                        6800.087232
                    ],
                    [
                        15324.576832,
                        6612.163776
                    ],
                    [
                        15268.588608,
                        6560.18496
                    ],
                    [
                        15160.611264,
                        6408.246912
                    ],
                    [
                        15104.62304,
                        6260.3072
                    ]
                ]
            ]
        }
    },
    {
        "geometry": {
            "coordinates": [
                [
                    [
                        15676.502976,
                        7739.704384
                    ],
                    [
                        15488.542464,
                        7771.691328
                    ],
                    [
                        15332.575168,
                        8019.590336
                    ],
                    [
                        15444.55168,
                        8383.442048
                    ],
                    [
                        15752.48704,
                        8443.4176
                    ],
                    [
                        15980.439168,
                        8323.466496
                    ],
                    [
                        16128.408128,
                        8135.54304
                    ],
                    [
                        16108.412288,
                        7991.601728
                    ],
                    [
                        15992.436672,
                        7851.658752
                    ],
                    [
                        15824.471936,
                        7791.6832
                    ],
                    [
                        15676.502976,
                        7739.704384
                    ]
                ]
            ]
        }
    },
    {
        "geometry": {
            "coordinates": [
                [
                    [
                        14936.658304,
                        8323.466496
                    ],
                    [
                        14660.716224,
                        8363.450176
                    ],
                    [
                        14460.758208,
                        8499.394816
                    ],
                    [
                        14380.774976,
                        8779.280768
                    ],
                    [
                        14500.749824,
                        9031.178112
                    ],
                    [
                        14764.6944,
                        9179.117824
                    ],
                    [
                        15004.644032,
                        9395.029824
                    ],
                    [
                        15072.62976,
                        9518.979328
                    ],
                    [
                        15108.622208,
                        9690.909312
                    ],
                    [
                        14536.742272,
                        9886.82944
                    ],
                    [
                        14320.787584,
                        9946.804992
                    ],
                    [
                        14180.81696,
                        10226.690944
                    ],
                    [
                        14192.814464,
                        10450.599744
                    ],
                    [
                        14520.7456,
                        10622.529664
                    ],
                    [
                        14836.679296,
                        10778.466112
                    ],
                    [
                        15004.644032,
                        10802.456384
                    ],
                    [
                        15172.608768,
                        10682.505216
                    ],
                    [
                        15220.59872,
                        10550.55904
                    ],
                    [
                        15356.570176,
                        10354.638848
                    ],
                    [
                        15556.528192,
                        10206.699136
                    ],
                    [
                        15688.50048,
                        10130.730048
                    ],
                    [
                        15872.461824,
                        10006.780608
                    ],
                    [
                        16100.414016,
                        9826.853888
                    ],
                    [
                        16184.396352,
                        9742.888128
                    ],
                    [
                        16256.381248,
                        9522.977728
                    ],
                    [
                        16064.421568,
                        9367.04128
                    ],
                    [
                        15792.478656,
                        9199.109696
                    ],
                    [
                        15500.539904,
                        9103.1488
                    ],
                    [
                        15408.559232,
                        8959.207424
                    ],
                    [
                        15376.565952,
                        8615.347584
                    ],
                    [
                        15256.591104,
                        8447.416
                    ],
                    [
                        15132.617152,
                        8331.463232
                    ],
                    [
                        14936.658304,
                        8323.466496
                    ]
                ]
            ]
        }
    },
    {
        "geometry": {
            "coordinates": [
                [
                    [
                        13680.92192,
                        7335.868928
                    ],
                    [
                        13452.969792,
                        7527.79072
                    ],
                    [
                        13348.991616,
                        7887.644096
                    ],
                    [
                        13364.988224,
                        8207.513728
                    ],
                    [
                        13508.958016,
                        8363.450176
                    ],
                    [
                        13740.909312,
                        8371.446912
                    ],
                    [
                        14008.305664,
                        8208.54176
                    ],
                    [
                        14124.281344,
                        8084.592256
                    ],
                    [
                        14288.246912,
                        7868.680256
                    ],
                    [
                        14380.227584,
                        7720.740544
                    ],
                    [
                        14672.166336,
                        7612.784512
                    ],
                    [
                        14792.14112,
                        7504.828544
                    ],
                    [
                        14808.137792,
                        7312.906752
                    ],
                    [
                        14592.183104,
                        7108.989824
                    ],
                    [
                        14368.230144,
                        7013.028928
                    ],
                    [
                        14200.265408,
                        7088.997952
                    ],
                    [
                        13964.314944,
                        7208.949056
                    ],
                    [
                        13944.319104,
                        7296.913216
                    ],
                    [
                        13680.92192,
                        7335.868928
                    ]
                ]
            ]
        }
    },
    {
        "geometry": {
            "coordinates": [
                [
                    [
                        11888.750656,
                        6853.09408
                    ],
                    [
                        11712.787584,
                        7096.994688
                    ],
                    [
                        11652.800192,
                        7496.831808
                    ],
                    [
                        11968.733888,
                        7624.779648
                    ],
                    [
                        12320.659968,
                        7708.745408
                    ],
                    [
                        12588.603712,
                        7668.761728
                    ],
                    [
                        12764.227584,
                        7480.711232
                    ],
                    [
                        12740.23264,
                        7208.822016
                    ],
                    [
                        12716.237696,
                        6980.91488
                    ],
                    [
                        12480.287232,
                        6824.978432
                    ],
                    [
                        12268.331712,
                        6784.994688
                    ],
                    [
                        12107.824512,
                        6808.983552
                    ],
                    [
                        11888.750656,
                        6853.09408
                    ]
                ]
            ]
        }
    },
    {
        "geometry": {
            "coordinates": [
                [
                    [
                        8181.193088,
                        6065.286336
                    ],
                    [
                        8625.099904,
                        6229.21952
                    ],
                    [
                        8973.02688,
                        6333.177152
                    ],
                    [
                        9101.0,
                        6365.16416
                    ],
                    [
                        9120.995776,
                        6605.066368
                    ],
                    [
                        9089.002496,
                        6780.994688
                    ],
                    [
                        9053.010048,
                        6924.936064
                    ],
                    [
                        9200.309056,
                        7132.312064
                    ],
                    [
                        9368.273792,
                        7172.295744
                    ],
                    [
                        9628.2192,
                        7136.3104
                    ],
                    [
                        9780.187328,
                        6956.383744
                    ],
                    [
                        9860.170496,
                        6708.484736
                    ],
                    [
                        9884.165504,
                        6400.610176
                    ],
                    [
                        9876.167168,
                        6212.686784
                    ],
                    [
                        9996.141952,
                        6072.743808
                    ],
                    [
                        10172.105024,
                        5976.782912
                    ],
                    [
                        10280.082368,
                        5908.810624
                    ],
                    [
                        10564.022784,
                        5780.86272
                    ],
                    [
                        10632.008512,
                        5632.923008
                    ],
                    [
                        10536.028608,
                        5337.043584
                    ],
                    [
                        10200.099136,
                        5201.098944
                    ],
                    [
                        9920.157952,
                        5169.112
                    ],
                    [
                        9640.216704,
                        5221.090816
                    ],
                    [
                        9412.264576,
                        5357.035456
                    ],
                    [
                        9300.288064,
                        5492.980032
                    ],
                    [
                        9124.324992,
                        5572.947456
                    ],
                    [
                        8812.390464,
                        5576.945856
                    ],
                    [
                        8600.435008,
                        5592.939328
                    ],
                    [
                        8340.489536,
                        5604.9344
                    ],
                    [
                        8104.539072,
                        5824.8448
                    ],
                    [
                        8181.193088,
                        6065.286336
                    ]
                ]
            ]
        }
    },
    {
        "geometry": {
            "coordinates": [
                [
                    [
                        6300.917696,
                        4577.353152
                    ],
                    [
                        6140.951296,
                        4741.286336
                    ],
                    [
                        5988.983232,
                        4897.222784
                    ],
                    [
                        5873.007552,
                        5061.155968
                    ],
                    [
                        5789.025216,
                        5281.066368
                    ],
                    [
                        5829.016768,
                        5496.978432
                    ],
                    [
                        5940.99328,
                        5756.872512
                    ],
                    [
                        6180.942912,
                        6028.761728
                    ],
                    [
                        6400.896704,
                        6048.7536
                    ],
                    [
                        6620.85056,
                        5916.80736
                    ],
                    [
                        6720.829568,
                        5816.848064
                    ],
                    [
                        6944.782528,
                        5716.888832
                    ],
                    [
                        7036.763264,
                        5660.911616
                    ],
                    [
                        7052.759872,
                        5540.960512
                    ],
                    [
                        7156.738048,
                        5153.118528
                    ],
                    [
                        7188.731328,
                        5065.154368
                    ],
                    [
                        7188.731328,
                        4929.209792
                    ],
                    [
                        7056.75904,
                        4677.312384
                    ],
                    [
                        6588.85728,
                        4537.369408
                    ],
                    [
                        6472.8816,
                        4533.371072
                    ],
                    [
                        6300.917696,
                        4577.353152
                    ]
                ]
            ]
        }
    },
    {
        "geometry": {
            "coordinates": [
                [
                    [
                        8044.55168,
                        3501.791424
                    ],
                    [
                        7804.602048,
                        3737.695296
                    ],
                    [
                        7764.610432,
                        3985.59424
                    ],
                    [
                        7976.565952,
                        4213.501376
                    ],
                    [
                        8280.502144,
                        4249.48672
                    ],
                    [
                        8456.465216,
                        4253.48512
                    ],
                    [
                        8776.398016,
                        4309.462272
                    ],
                    [
                        8904.3712,
                        4321.457408
                    ],
                    [
                        9076.33504,
                        4249.48672
                    ],
                    [
                        9136.322496,
                        4097.548672
                    ],
                    [
                        9116.326656,
                        3917.621952
                    ],
                    [
                        8960.359424,
                        3649.731136
                    ],
                    [
                        8660.4224,
                        3569.763712
                    ],
                    [
                        8504.455104,
                        3465.80608
                    ],
                    [
                        8300.49792,
                        3361.848448
                    ],
                    [
                        8156.528192,
                        3397.833728
                    ],
                    [
                        8044.55168,
                        3501.791424
                    ]
                ]
            ]
        }
    },
    {
        "geometry": {
            "coordinates": [
                [
                    [
                        10260.549184,
                        2598.149824
                    ],
                    [
                        10232.555008,
                        2758.084672
                    ],
                    [
                        10200.561728,
                        2926.016256
                    ],
                    [
                        10332.534016,
                        3137.929856
                    ],
                    [
                        10280.54496,
                        3417.815808
                    ],
                    [
                        10280.54496,
                        3593.744128
                    ],
                    [
                        10400.519744,
                        3793.66272
                    ],
                    [
                        10604.476928,
                        3901.618688
                    ],
                    [
                        10848.425728,
                        3901.618688
                    ],
                    [
                        11036.386304,
                        3809.656192
                    ],
                    [
                        11160.360256,
                        3649.721344
                    ],
                    [
                        11160.360256,
                        3465.796288
                    ],
                    [
                        11068.379584,
                        3289.867968
                    ],
                    [
                        11020.389632,
                        3105.942912
                    ],
                    [
                        11124.367808,
                        2965.999936
                    ],
                    [
                        11172.35776,
                        2810.063488
                    ],
                    [
                        10788.34848,
                        2544.906752
                    ],
                    [
                        10576.393024,
                        2504.923008
                    ],
                    [
                        10404.42912,
                        2512.919744
                    ],
                    [
                        10260.549184,
                        2598.149824
                    ]
                ]
            ]
        }
    },
    {
        "geometry": {
            "coordinates": [
                [
                    [
                        12240.093248,
                        4176.413056
                    ],
                    [
                        11860.173056,
                        4176.413056
                    ],
                    [
                        11604.226752,
                        4260.37888
                    ],
                    [
                        11440.261184,
                        4524.271296
                    ],
                    [
                        11488.251136,
                        4780.16704
                    ],
                    [
                        11724.48704,
                        5000.377216
                    ],
                    [
                        12152.397184,
                        5084.34304
                    ],
                    [
                        12744.268736,
                        5120.32672
                    ],
                    [
                        13108.19232,
                        4972.387008
                    ],
                    [
                        13232.166336,
                        4856.43424
                    ],
                    [
                        13364.138624,
                        4564.553216
                    ],
                    [
                        12808.255296,
                        4180.709568
                    ],
                    [
                        12488.325824,
                        4180.712832
                    ],
                    [
                        12404.343488,
                        4212.69984
                    ],
                    [
                        12240.093248,
                        4176.413056
                    ]
                ]
            ]
        }
    },
    {
        "geometry": {
            "coordinates": [
                [
                    [
                        14079.99168,
                        3185.118528
                    ],
                    [
                        13932.022784,
                        3405.028928
                    ],
                    [
                        13832.043776,
                        3564.963776
                    ],
                    [
                        13692.073152,
                        3768.88064
                    ],
                    [
                        13548.10336,
                        4040.769856
                    ],
                    [
                        13564.099968,
                        4252.68352
                    ],
                    [
                        13652.081536,
                        4428.61184
                    ],
                    [
                        14127.981632,
                        4560.55808
                    ],
                    [
                        14311.942976,
                        4496.584128
                    ],
                    [
                        14479.907712,
                        4312.659072
                    ],
                    [
                        14575.887616,
                        4172.716096
                    ],
                    [
                        14643.873344,
                        3948.80736
                    ],
                    [
                        14723.856512,
                        3808.864384
                    ],
                    [
                        14699.861568,
                        3508.98656
                    ],
                    [
                        14591.884224,
                        3317.064768
                    ],
                    [
                        14415.921152,
                        3225.102208
                    ],
                    [
                        14239.95808,
                        3169.125056
                    ],
                    [
                        14079.99168,
                        3185.118528
                    ]
                ]
            ]
        }
    },
    {
        "geometry": {
            "coordinates": [
                [
                    [
                        3576.8976,
                        5232.621632
                    ],
                    [
                        3784.853888,
                        5444.535232
                    ],
                    [
                        3888.832064,
                        5660.447296
                    ],
                    [
                        3988.811072,
                        5892.352768
                    ],
                    [
                        4240.758208,
                        6032.295744
                    ],
                    [
                        4620.678464,
                        6136.253376
                    ],
                    [
                        4944.610432,
                        6092.271296
                    ],
                    [
                        5096.57856,
                        5996.3104
                    ],
                    [
                        5120.573504,
                        5692.43424
                    ],
                    [
                        5012.59616,
                        5352.572736
                    ],
                    [
                        4780.644864,
                        5140.659072
                    ],
                    [
                        4472.709504,
                        4980.724224
                    ],
                    [
                        4224.761536,
                        4892.760128
                    ],
                    [
                        4120.783424,
                        4980.724224
                    ],
                    [
                        4080.791808,
                        5056.693312
                    ],
                    [
                        3956.817792,
                        5044.698176
                    ],
                    [
                        3848.840512,
                        4952.73568
                    ],
                    [
                        3620.88832,
                        4952.73568
                    ],
                    [
                        3472.919424,
                        5028.704704
                    ],
                    [
                        3404.933696,
                        5124.6656
                    ],
                    [
                        3576.8976,
                        5232.621632
                    ]
                ]
            ]
        }
    },
    {
        "geometry": {
            "coordinates": [
                [
                    [
                        2641.094016,
                        6184.233856
                    ],
                    [
                        2885.042816,
                        6324.176832
                    ],
                    [
                        3073.003328,
                        6408.142592
                    ],
                    [
                        3136.989952,
                        6572.07584
                    ],
                    [
                        3132.990784,
                        6815.976448
                    ],
                    [
                        3184.97984,
                        6903.940608
                    ],
                    [
                        3436.15456,
                        6884.800832
                    ],
                    [
                        3684.102528,
                        6848.815488
                    ],
                    [
                        3852.067264,
                        6840.818752
                    ],
                    [
                        4056.024448,
                        6920.786176
                    ],
                    [
                        4164.001792,
                        7060.729152
                    ],
                    [
                        4199.99424,
                        7312.626496
                    ],
                    [
                        4092.016896,
                        7544.532032
                    ],
                    [
                        3940.048768,
                        7628.497792
                    ],
                    [
                        3616.1168,
                        7660.484736
                    ],
                    [
                        3516.137792,
                        7696.47008
                    ],
                    [
                        3404.16128,
                        7664.483136
                    ],
                    [
                        3148.21504,
                        7516.543424
                    ],
                    [
                        3040.237696,
                        7488.554816
                    ],
                    [
                        2832.281344,
                        7524.54016
                    ],
                    [
                        2632.323328,
                        7568.52224
                    ],
                    [
                        2528.345152,
                        7524.54016
                    ],
                    [
                        2340.384576,
                        7456.567872
                    ],
                    [
                        2212.411456,
                        7456.567872
                    ],
                    [
                        1976.460992,
                        7464.564608
                    ],
                    [
                        1824.492928,
                        7460.566208
                    ],
                    [
                        1640.53152,
                        7340.615104
                    ],
                    [
                        1648.529856,
                        7156.690048
                    ],
                    [
                        2100.435008,
                        6940.778048
                    ],
                    [
                        2392.373696,
                        6816.828544
                    ],
                    [
                        2404.3712,
                        6680.883904
                    ],
                    [
                        2400.372032,
                        6480.965376
                    ],
                    [
                        2388.374528,
                        6333.025664
                    ],
                    [
                        2440.363584,
                        6285.045184
                    ],
                    [
                        2641.094016,
                        6184.233856
                    ]
                ]
            ]
        }
    },
    {
        "geometry": {
            "coordinates": [
                [
                    [
                        4475.936256,
                        9119.890112
                    ],
                    [
                        4108.013504,
                        9127.886848
                    ],
                    [
                        3908.055488,
                        9251.836352
                    ],
                    [
                        3800.078144,
                        9447.75648
                    ],
                    [
                        3860.0656,
                        9699.653824
                    ],
                    [
                        4215.990848,
                        9815.606592
                    ],
                    [
                        4471.937152,
                        9847.5936
                    ],
                    [
                        4739.880896,
                        9879.580544
                    ],
                    [
                        4847.858176,
                        9839.5968
                    ],
                    [
                        4887.849792,
                        9707.65056
                    ],
                    [
                        4891.84896,
                        9563.709248
                    ],
                    [
                        4807.866624,
                        9367.789056
                    ],
                    [
                        4711.88672,
                        9267.829824
                    ],
                    [
                        4539.92288,
                        9195.859136
                    ],
                    [
                        4475.936256,
                        9119.890112
                    ]
                ]
            ]
        }
    },
    {
        "geometry": {
            "coordinates": [
                [
                    [
                        4759.876672,
                        7748.448896
                    ],
                    [
                        4655.898496,
                        7992.349504
                    ],
                    [
                        4539.92288,
                        8208.261568
                    ],
                    [
                        4459.939648,
                        8388.188224
                    ],
                    [
                        4563.917824,
                        8636.087232
                    ],
                    [
                        4751.878336,
                        8740.044864
                    ],
                    [
                        5087.807808,
                        8744.043264
                    ],
                    [
                        5315.76,
                        8724.051392
                    ],
                    [
                        5615.697024,
                        8584.108416
                    ],
                    [
                        5743.670144,
                        8408.180096
                    ],
                    [
                        5775.663424,
                        8184.271296
                    ],
                    [
                        5639.691968,
                        7868.400064
                    ],
                    [
                        5467.728064,
                        7724.458688
                    ],
                    [
                        5151.794368,
                        7684.475008
                    ],
                    [
                        4987.8288,
                        7668.481472
                    ],
                    [
                        4759.876672,
                        7748.448896
                    ]
                ]
            ]
        }
    },
    {
        "geometry": {
            "coordinates": [
                [
                    [
                        6771.4544,
                        7992.349504
                    ],
                    [
                        6459.519872,
                        8064.320192
                    ],
                    [
                        6367.5392,
                        8196.266432
                    ],
                    [
                        6291.555136,
                        8444.16544
                    ],
                    [
                        6435.524928,
                        8652.080704
                    ],
                    [
                        6655.47872,
                        8844.002496
                    ],
                    [
                        6891.429184,
                        8824.010624
                    ],
                    [
                        7087.388032,
                        8732.048128
                    ],
                    [
                        7227.358656,
                        8508.139392
                    ],
                    [
                        7163.372096,
                        8292.227328
                    ],
                    [
                        6943.418304,
                        8040.329984
                    ],
                    [
                        6771.4544,
                        7992.349504
                    ]
                ]
            ]
        }
    },
    {
        "geometry": {
            "coordinates": [
                [
                    [
                        7651.269696,
                        6588.921408
                    ],
                    [
                        7495.3024,
                        6776.8448
                    ],
                    [
                        7443.313344,
                        7012.748672
                    ],
                    [
                        7603.279744,
                        7276.641152
                    ],
                    [
                        7579.2848,
                        7540.533632
                    ],
                    [
                        7507.299904,
                        7712.463552
                    ],
                    [
                        7379.326784,
                        7944.369088
                    ],
                    [
                        7343.334336,
                        8100.305536
                    ],
                    [
                        7383.325952,
                        8252.243648
                    ],
                    [
                        7663.267136,
                        8292.227328
                    ],
                    [
                        7863.225152,
                        8252.243648
                    ],
                    [
                        8031.189888,
                        8132.29248
                    ],
                    [
                        8303.1328,
                        8048.32672
                    ],
                    [
                        8391.114368,
                        7808.424448
                    ],
                    [
                        8315.130304,
                        7576.518976
                    ],
                    [
                        8079.17984,
                        7336.616704
                    ],
                    [
                        8231.147968,
                        7164.686784
                    ],
                    [
                        8375.117696,
                        6984.760128
                    ],
                    [
                        8415.109312,
                        6872.805696
                    ],
                    [
                        8211.152128,
                        6532.944192
                    ],
                    [
                        8091.177344,
                        6568.929536
                    ],
                    [
                        7839.230208,
                        6564.931136
                    ],
                    [
                        7651.269696,
                        6588.921408
                    ]
                ]
            ]
        }
    },
    {
        "geometry": {
            "coordinates": [
                [
                    [
                        8999.080768,
                        8724.347904
                    ],
                    [
                        8895.102592,
                        8980.243648
                    ],
                    [
                        8703.142912,
                        9156.171968
                    ],
                    [
                        8283.23104,
                        9204.152384
                    ],
                    [
                        8095.270528,
                        9579.999232
                    ],
                    [
                        8287.230208,
                        9779.91776
                    ],
                    [
                        8811.120256,
                        9839.893376
                    ],
                    [
                        9191.040448,
                        9743.93248
                    ],
                    [
                        9347.007744,
                        9639.974784
                    ],
                    [
                        9590.956544,
                        9264.127936
                    ],
                    [
                        9558.963264,
                        8996.23712
                    ],
                    [
                        9406.995136,
                        8800.316928
                    ],
                    [
                        9231.032064,
                        8740.341376
                    ],
                    [
                        9067.066496,
                        8740.341376
                    ],
                    [
                        8999.080768,
                        8724.347904
                    ]
                ]
            ]
        }
    },
    {
        "geometry": {
            "coordinates": [
                [
                    [
                        10494.766784,
                        9148.175232
                    ],
                    [
                        10262.815488,
                        9240.137728
                    ],
                    [
                        10098.84992,
                        9328.101888
                    ],
                    [
                        10082.853248,
                        9568.00416
                    ],
                    [
                        10154.838144,
                        9807.906368
                    ],
                    [
                        10314.804544,
                        9931.855872
                    ],
                    [
                        10714.720576,
                        9955.84608
                    ],
                    [
                        11022.655936,
                        9899.868928
                    ],
                    [
                        11102.639168,
                        9683.956864
                    ],
                    [
                        11086.642496,
                        9452.051392
                    ],
                    [
                        11006.659328,
                        9292.116544
                    ],
                    [
                        10854.6912,
                        9228.142592
                    ],
                    [
                        10630.73824,
                        9188.158912
                    ],
                    [
                        10494.766784,
                        9148.175232
                    ]
                ]
            ]
        }
    },
    {
        "geometry": {
            "coordinates": [
                [
                    [
                        11514.552704,
                        8104.600448
                    ],
                    [
                        11374.58208,
                        8408.476608
                    ],
                    [
                        11474.561088,
                        8636.383744
                    ],
                    [
                        11722.509056,
                        8588.403264
                    ],
                    [
                        11978.455296,
                        8496.440768
                    ],
                    [
                        12062.437696,
                        8444.461952
                    ],
                    [
                        12214.40576,
                        8284.527104
                    ],
                    [
                        12218.404928,
                        8196.562944
                    ],
                    [
                        12046.441024,
                        7992.64608
                    ],
                    [
                        11938.46368,
                        7960.659072
                    ],
                    [
                        11702.513216,
                        7984.64928
                    ],
                    [
                        11570.540928,
                        8076.61184
                    ],
                    [
                        11514.552704,
                        8104.600448
                    ]
                ]
            ]
        }
    },
    {
        "geometry": {
            "coordinates": [
                [
                    [
                        5351.846464,
                        10407.662016
                    ],
                    [
                        5187.880896,
                        10571.5952
                    ],
                    [
                        5251.867456,
                        10823.492544
                    ],
                    [
                        5495.816256,
                        10983.427392
                    ],
                    [
                        5915.728064,
                        11075.389888
                    ],
                    [
                        6135.68192,
                        10991.424128
                    ],
                    [
                        6327.6416,
                        10811.497472
                    ],
                    [
                        6315.644096,
                        10675.552832
                    ],
                    [
                        6255.656704,
                        10615.57728
                    ],
                    [
                        5959.718848,
                        10491.627776
                    ],
                    [
                        5835.744832,
                        10487.62944
                    ],
                    [
                        5655.782656,
                        10487.62944
                    ],
                    [
                        5443.827136,
                        10471.635904
                    ],
                    [
                        5351.846464,
                        10407.662016
                    ]
                ]
            ]
        }
    },
    {
        "geometry": {
            "coordinates": [
                [
                    [
                        6903.520704,
                        10835.48768
                    ],
                    [
                        6719.559296,
                        10883.468096
                    ],
                    [
                        6615.58112,
                        11031.407808
                    ],
                    [
                        6711.561024,
                        11223.329664
                    ],
                    [
                        6775.547584,
                        11363.27264
                    ],
                    [
                        6963.508096,
                        11431.244928
                    ],
                    [
                        7203.457728,
                        11483.223744
                    ],
                    [
                        7395.417408,
                        11411.253056
                    ],
                    [
                        7323.432576,
                        11175.349184
                    ],
                    [
                        7160.455104,
                        11012.799168
                    ],
                    [
                        7088.470208,
                        10960.820352
                    ],
                    [
                        6903.520704,
                        10835.48768
                    ]
                ]
            ]
        }
    },
    {
        "geometry": {
            "coordinates": [
                [
                    [
                        7816.31744,
                        10540.991424
                    ],
                    [
                        7556.372032,
                        10696.927936
                    ],
                    [
                        7436.397184,
                        10984.810624
                    ],
                    [
                        7532.377024,
                        11324.672128
                    ],
                    [
                        7828.314944,
                        11504.598784
                    ],
                    [
                        8216.233472,
                        11644.54176
                    ],
                    [
                        8492.175552,
                        11696.520576
                    ],
                    [
                        8944.271296,
                        11768.530368
                    ],
                    [
                        9164.225088,
                        11844.499392
                    ],
                    [
                        9464.162112,
                        11924.466816
                    ],
                    [
                        9624.128512,
                        11968.448896
                    ],
                    [
                        9848.081536,
                        12044.417984
                    ],
                    [
                        10016.046272,
                        12144.377216
                    ],
                    [
                        10307.98496,
                        12576.20128
                    ],
                    [
                        10663.910272,
                        12704.14912
                    ],
                    [
                        10967.846464,
                        12952.048128
                    ],
                    [
                        11363.763328,
                        12960.044864
                    ],
                    [
                        11603.71296,
                        12852.088832
                    ],
                    [
                        11863.658368,
                        12652.170304
                    ],
                    [
                        12087.611392,
                        12504.230592
                    ],
                    [
                        12379.55008,
                        12248.334848
                    ],
                    [
                        12419.541696,
                        11728.546688
                    ],
                    [
                        12307.565184,
                        11348.70144
                    ],
                    [
                        12103.608,
                        11168.774784
                    ],
                    [
                        11795.67264,
                        11164.776384
                    ],
                    [
                        11483.738176,
                        11208.758464
                    ],
                    [
                        11323.771712,
                        11388.68512
                    ],
                    [
                        11043.830528,
                        11540.623232
                    ],
                    [
                        10523.939648,
                        11544.621632
                    ],
                    [
                        10375.970688,
                        11540.623232
                    ],
                    [
                        10176.012672,
                        11704.556416
                    ],
                    [
                        9784.094976,
                        11460.655808
                    ],
                    [
                        9528.148672,
                        11224.751936
                    ],
                    [
                        9236.209984,
                        10988.848064
                    ],
                    [
                        9296.197376,
                        10768.937664
                    ],
                    [
                        9488.157056,
                        10533.033792
                    ],
                    [
                        9640.125184,
                        10305.126656
                    ],
                    [
                        9528.148672,
                        10065.224448
                    ],
                    [
                        9336.188992,
                        10049.230912
                    ],
                    [
                        8976.264576,
                        10173.180416
                    ],
                    [
                        8748.312384,
                        10349.108736
                    ],
                    [
                        8672.328384,
                        10529.035456
                    ],
                    [
                        8532.35776,
                        10605.00448
                    ],
                    [
                        8172.43328,
                        10605.00448
                    ],
                    [
                        7964.476928,
                        10505.045184
                    ],
                    [
                        7816.31744,
                        10540.991424
                    ]
                ]
            ]
        }
    },
    {
        "geometry": {
            "coordinates": [
                [
                    [
                        9040.251136,
                        12244.336512
                    ],
                    [
                        8636.335936,
                        12340.297408
                    ],
                    [
                        8296.407296,
                        12420.264832
                    ],
                    [
                        8424.380416,
                        12820.101888
                    ],
                    [
                        8688.324992,
                        13000.028544
                    ],
                    [
                        9140.230144,
                        12824.100288
                    ],
                    [
                        9408.173888,
                        12640.175232
                    ],
                    [
                        9464.162112,
                        12484.23872
                    ],
                    [
                        9392.177216,
                        12244.336512
                    ],
                    [
                        9184.220864,
                        12228.34304
                    ],
                    [
                        9040.251136,
                        12244.336512
                    ]
                ]
            ]
        }
    },
    {
        "geometry": {
            "coordinates": [
                [
                    [
                        13843.242816,
                        10529.035456
                    ],
                    [
                        13691.274688,
                        10768.937664
                    ],
                    [
                        13691.274688,
                        10948.864384
                    ],
                    [
                        13731.266304,
                        11080.810624
                    ],
                    [
                        14015.20672,
                        11096.804096
                    ],
                    [
                        14144.162112,
                        11044.4864
                    ],
                    [
                        14192.152064,
                        10832.572736
                    ],
                    [
                        14152.160448,
                        10672.637888
                    ],
                    [
                        14036.184768,
                        10504.706304
                    ],
                    [
                        13843.242816,
                        10529.035456
                    ]
                ]
            ]
        }
    },
    {
        "geometry": {
            "coordinates": [
                [
                    [
                        17374.385536,
                        7750.8736
                    ],
                    [
                        17042.455232,
                        7710.882112
                    ],
                    [
                        16738.51904,
                        7794.864256
                    ],
                    [
                        16466.576128,
                        7938.833664
                    ],
                    [
                        16386.592896,
                        8194.779264
                    ],
                    [
                        16346.60128,
                        8682.675584
                    ],
                    [
                        16366.59712,
                        8954.617792
                    ],
                    [
                        16386.592896,
                        9106.585472
                    ],
                    [
                        16406.588736,
                        9230.559168
                    ],
                    [
                        16486.571904,
                        9298.544704
                    ],
                    [
                        16646.538304,
                        9166.572736
                    ],
                    [
                        16826.500544,
                        8894.630528
                    ],
                    [
                        16906.483776,
                        8810.648384
                    ],
                    [
                        17126.437568,
                        8810.648384
                    ],
                    [
                        17334.39392,
                        8614.690048
                    ],
                    [
                        17226.416576,
                        8466.721472
                    ],
                    [
                        17306.399808,
                        8254.766528
                    ],
                    [
                        17382.383872,
                        8114.796288
                    ],
                    [
                        17434.372928,
                        7914.838784
                    ],
                    [
                        17374.385536,
                        7750.8736
                    ]
                ]
            ]
        }
    },
    {
        "geometry": {
            "coordinates": [
                [
                    [
                        11071.592832,
                        10315.337344
                    ],
                    [
                        10931.622208,
                        10435.311872
                    ],
                    [
                        10883.632256,
                        10669.262144
                    ],
                    [
                        11043.59872,
                        10833.227328
                    ],
                    [
                        11245.556288,
                        10905.212032
                    ],
                    [
                        11453.51264,
                        10775.239616
                    ],
                    [
                        11541.494144,
                        10531.291456
                    ],
                    [
                        11411.521472,
                        10311.33824
                    ],
                    [
                        11317.541184,
                        10267.347584
                    ],
                    [
                        11179.570176,
                        10271.346752
                    ],
                    [
                        11071.592832,
                        10315.337344
                    ]
                ]
            ]
        }
    }
]