[
    {
        "geometry": {
            "coordinates": [
                [
                    [
                        1259.64064,
                        1038.945344
                    ],
                    [
                        1274.64064,
                        1111.945344
                    ],
                    [
                        1292.64064,
                        1154.945344
                    ],
                    [
                        1277.64064,
                        1168.945344
                    ],
                    [
                        1295.64064,
                        1210.945344
                    ],
                    [
                        1301.64064,
                        1275.945344
                    ],
                    [
                        1249.64064,
                        1335.945344
                    ],
                    [
                        1223.64064,
                        1289.945344
                    ],
                    [
                        1187.64064,
                        1184.945344
                    ],
                    [
                        1167.64064,
                        1156.945344
                    ],
                    [
                        1172.64064,
                        1110.945344
                    ],
                    [
                        1187.64064,
                        1067.945344
                    ],
                    [
                        1209.64064,
                        1024.945344
                    ],
                    [
                        1229.64064,
                        1019.945344
                    ],
                    [
                        1239.64064,
                        1036.945344
                    ],
                    [
                        1259.64064,
                        1038.945344
                    ]
                ]
            ]
        }
    },
    {
        "geometry": {
            "coordinates": [
                [
                    [
                        1684.015616,
                        1312.988288
                    ],
                    [
                        1698.015616,
                        1334.988288
                    ],
                    [
                        1711.015616,
                        1334.988288
                    ],
                    [
                        1719.015616,
                        1366.988288
                    ],
                    [
                        1680.015616,
                        1369.988288
                    ],
                    [
                        1674.015616,
                        1438.988288
                    ],
                    [
                        1711.015616,
                        1479.988288
                    ],
                    [
                        1714.015616,
                        1506.988288
                    ],
                    [
                        1706.015616,
                        1607.988288
                    ],
                    [
                        1651.015616,
                        1617.988288
                    ],
                    [
                        1597.015616,
                        1669.988288
                    ],
                    [
                        1565.015616,
                        1635.988288
                    ],
                    [
                        1542.015616,
                        1535.988288
                    ],
                    [
                        1507.015616,
                        1472.988288
                    ],
                    [
                        1518.015616,
                        1355.988288
                    ],
                    [
                        1532.015616,
                        1331.988288
                    ],
                    [
                        1598.015616,
                        1298.988288
                    ],
                    [
                        1646.015616,
                        1298.988288
                    ],
                    [
                        1684.015616,
                        1312.988288
                    ]
                ]
            ]
        }
    },
    {
        "geometry": {
            "coordinates": [
                [
                    [
                        1031.0,
                        1593.0
                    ],
                    [
                        1029.0,
                        1557.0
                    ],
                    [
                        1048.0,
                        1513.0
                    ],
                    [
                        1070.0,
                        1493.0
                    ],
                    [
                        1086.0,
                        1492.0
                    ],
                    [
                        1095.0,
                        1529.0
                    ],
                    [
                        1115.0,
                        1475.0
                    ],
                    [
                        1135.0,
                        1422.0
                    ],
                    [
                        1128.0,
                        1395.0
                    ],
                    [
                        1090.0,
                        1377.0
                    ],
                    [
                        1030.0,
                        1434.0
                    ],
                    [
                        998.0,
                        1476.0
                    ],
                    [
                        1011.0,
                        1506.0
                    ],
                    [
                        1019.0,
                        1542.0
                    ],
                    [
                        1018.0,
                        1573.0
                    ],
                    [
                        1031.0,
                        1593.0
                    ]
                ]
            ]
        }
    }
]